tautoolbox/__init__.py
tautoolbox/_version.py
tautoolbox/conftest.py
tautoolbox/functions.py
tautoolbox/polynomial/__init__.py
tautoolbox/polynomial/bases.py
tautoolbox/polynomial/options.py
tautoolbox/polynomial/polynomial1.py
tautoolbox/polynomial/polynomial2.py
tautoolbox/polynomial/polynomial3.py
tautoolbox/tau/__init__.py
tautoolbox/tau/condition.py
tautoolbox/tau/eig.py
tautoolbox/tau/equation.py
tautoolbox/tau/equation2.py
tautoolbox/tau/lines_function.py
tautoolbox/tau/matrix.py
tautoolbox/tau/ode.py
tautoolbox/tau/operator.py
tautoolbox/tau/operator2.py
tautoolbox/tau/options.py
tautoolbox/tau/pde.py
tautoolbox/tau/problem.py
tautoolbox/tau/problem2.py
tautoolbox/tau/solvers.py
tautoolbox/tau/utils.py
tautoolbox/utils.py
tautoolbox-0.90.0.dist-info/WHEEL
tautoolbox-0.90.0.dist-info/METADATA
tautoolbox-0.90.0.dist-info/RECORD
