Metadata-Version: 2.3
Name: tautoolbox
Version: 0.90.0
Summary: A package that implements Lanczos' Tau method to solve differential problems
Author: José Matos, Paulo Vasconcelos
Author-email: José Matos <jamatos@fep.up.pt>, Paulo Vasconcelos <pjv@fep.up.pt>
License:                    GNU LESSER GENERAL PUBLIC LICENSE
Classifier: Development Status :: 1 - Planning
Classifier: Intended Audience :: Science/Research
Classifier: Intended Audience :: Developers
Classifier: License :: OSI Approved :: GNU Lesser General Public License v3 (LGPLv3)
Classifier: Operating System :: OS Independent
Classifier: Programming Language :: Python
Classifier: Programming Language :: Python :: 3
Classifier: Programming Language :: Python :: 3 :: Only
Classifier: Programming Language :: Python :: 3.10
Classifier: Programming Language :: Python :: 3.11
Classifier: Programming Language :: Python :: 3.12
Classifier: Programming Language :: Python :: 3.13
Classifier: Topic :: Scientific/Engineering
Classifier: Typing :: Typed
Requires-Dist: numpy
Requires-Dist: matplotlib
Requires-Python: >=3.10
Project-URL: Homepage, https://cmup.fc.up.pt/tautoolbox/
